{"cameraMode":{"drawMode":0,"name":"Shaded","section":"Shading Mode"},"sceneLighting":true,"audioPlay":false,"sceneViewState":{"m_AlwaysRefresh":false,"showFog":true,"showSkybox":true,"showFlares":true,"showImageEffects":true,"showParticleSystems":true,"showVisualEffectGraphs":true,"m_FxEnabled":true},"in2DMode":false,"pivot":{"x":21.15534019470215,"y":-15.919646263122559,"z":-7.125034809112549},"rotation":{"x":0.1723945438861847,"y":0.8251175284385681,"z":-0.3435581922531128,"w":0.4140412211418152},"size":18.5927791595459,"orthographic":false}