[
    {
        "ID": 10001,
        "Prefab": "prefab",
        "Icon": "icon",
        "Name": "猛攻",
        "TargetType": 0,
        "Desc": "对指定敌人造成伤害",
        "Params": null
    },
    {
        "ID": 10002,
        "Prefab": "prefab",
        "Icon": "icon",
        "Name": "单体恢复",
        "TargetType": 1,
        "Desc": "回复指定队友血量",
        "Params": null
    },
    {
        "ID": 10003,
        "Prefab": "prefab",
        "Icon": "icon",
        "Name": "突袭后撤",
        "TargetType": 0,
        "Desc": "攻击后增加行动至指定位置",
        "Params": null
    },
    {
        "ID": 10004,
        "Prefab": "prefab",
        "Icon": "icon",
        "Name": "连锁攻击",
        "TargetType": 0,
        "Desc": "对目标敌人及附近区域敌人造成伤害",
        "Params": null
    },
    {
        "ID": 10005,
        "Prefab": "prefab",
        "Icon": "icon",
        "Name": "激励",
        "TargetType": 1,
        "Desc": "恢复全体队友怒气值",
        "Params": null
    },
    {
        "ID": 10006,
        "Prefab": "prefab",
        "Icon": "icon",
        "Name": "潜行",
        "TargetType": 1,
        "Desc": "当前回合不可见",
        "Params": null
    },
    {
        "ID": 10007,
        "Prefab": "prefab",
        "Icon": "icon",
        "Name": "致命一击",
        "TargetType": 0,
        "Desc": "敌人产生超高伤害",
        "Params": [
            200
        ]
    },
    {
        "ID": 10008,
        "Prefab": "prefab",
        "Icon": "icon",
        "Name": "幻影",
        "TargetType": 1,
        "Desc": "分裂出自身英雄",
        "Params": [
            10025
        ]
    },
    {
        "ID": 10009,
        "Prefab": "prefab",
        "Icon": "icon",
        "Name": "晕眩",
        "TargetType": 0,
        "Desc": "让敌方当前回合不可行动",
        "Params": null
    },
    {
        "ID": 10010,
        "Prefab": "prefab",
        "Icon": "icon",
        "Name": "额外行动",
        "TargetType": 1,
        "Desc": "给指定队友增加一次行动",
        "Params": null
    },
    {
        "ID": 10011,
        "Prefab": "prefab",
        "Icon": "icon",
        "Name": "钢铁壁垒",
        "TargetType": 1,
        "Desc": "给全部队友加护盾",
        "Params": null
    },
    {
        "ID": 10012,
        "Prefab": "prefab",
        "Icon": "icon",
        "Name": "迷惑",
        "TargetType": 0,
        "Desc": "一定概率让敌人当前回合攻击目标变为队友",
        "Params": null
    },
    {
        "ID": 10013,
        "Prefab": "prefab",
        "Icon": "icon",
        "Name": "命运赌盘",
        "TargetType": 0,
        "Desc": "以全部血量的一半为代价，赌敌人自身剩余全部血量",
        "Params": null
    },
    {
        "ID": 10014,
        "Prefab": "prefab",
        "Icon": "icon",
        "Name": "生命汲取",
        "TargetType": 0,
        "Desc": "将对敌人的伤害转化为自身血量",
        "Params": null
    },
    {
        "ID": 10015,
        "Prefab": "prefab",
        "Icon": "icon",
        "Name": "群体恢复",
        "TargetType": 1,
        "Desc": "恢复全体队友血量",
        "Params": null
    },
    {
        "ID": 10016,
        "Prefab": "prefab",
        "Icon": "icon",
        "Name": "钢铁守护",
        "TargetType": 1,
        "Desc": "给指定队友加护盾",
        "Params": null
    },
    {
        "ID": 10017,
        "Prefab": "prefab",
        "Icon": "icon",
        "Name": "怒气消减",
        "TargetType": 0,
        "Desc": "降低敌方全体怒气值",
        "Params": null
    },
    {
        "ID": 10018,
        "Prefab": "prefab",
        "Icon": "icon",
        "Name": "魔法庇护",
        "TargetType": 1,
        "Desc": "给全部队友加魔法护盾",
        "Params": null
    },
    {
        "ID": 10019,
        "Prefab": "prefab",
        "Icon": "icon",
        "Name": "法力屏障",
        "TargetType": 1,
        "Desc": "对指定队友加魔法护盾",
        "Params": null
    }
]